LICENSE
MANIFEST.in
setup.py
taiga_contrib_ldap_auth/__init__.py
taiga_contrib_ldap_auth/apps.py
taiga_contrib_ldap_auth/connector.py
taiga_contrib_ldap_auth/services.py
taiga_contrib_ldap_auth.egg-info/PKG-INFO
taiga_contrib_ldap_auth.egg-info/SOURCES.txt
taiga_contrib_ldap_auth.egg-info/dependency_links.txt
taiga_contrib_ldap_auth.egg-info/requires.txt
taiga_contrib_ldap_auth.egg-info/top_level.txt