Metadata-Version: 1.1
Name: taiga-contrib-ldap-auth
Version: 0.0.6
Summary: The Taiga plugin for ldap authentication
Home-page: https://ldap.com/taigaio/taiga-contrib-ldap-auth
Author: enskylin
Author-email: enskylin@synology.com
License: AGPL
Keywords: taiga,ldap,auth,plugin
Platform: UNKNOWN
Classifier: Programming Language :: Python
Classifier: Development Status :: 4 - Beta
Classifier: Framework :: Django
Classifier: Intended Audience :: Developers
Classifier: License :: OSI Approved :: GNU Affero General Public License v3
Classifier: Operating System :: OS Independent
Classifier: Programming Language :: Python
Classifier: Topic :: Internet :: WWW/HTTP
